setup.py
PCA9685_driver_http.egg-info/PKG-INFO
PCA9685_driver_http.egg-info/SOURCES.txt
PCA9685_driver_http.egg-info/dependency_links.txt
PCA9685_driver_http.egg-info/requires.txt
PCA9685_driver_http.egg-info/top_level.txt
pca9685_driver_http/__init__.py
pca9685_driver_http/app.py
pca9685_driver_http/config.py
pca9685_driver_http/controllers.py
pca9685_driver_http/error_handlers.py
pca9685_driver_http/http.py
pca9685_driver_http/teve.py