Metadata-Version: 1.0
Name: PCA9685-driver-http
Version: 1.0.2
Summary: Web interface for PCA9685 pwm (LED/Servo) controller
Home-page: https://github.com/voidpp/PCA9685-driver-http.git
Author: Lajos Santa
Author-email: santa.lajos@coldline.hu
License: UNKNOWN
Platform: UNKNOWN
